Metadata-Version: 1.1
Name: gconsul
Version: 0.0.1
Summary: gevent version for python-consul
Home-page: https://github.com/may-day/gconsul
Author: Norman Krämer
Author-email: kraemer.norman@gmail.com
License: MIT
Platform: UNKNOWN
Classifier: License :: OSI Approved :: MIT License
Classifier: Programming Language :: Python :: 3
Classifier: Development Status :: 3 - Alpha
Classifier: Intended Audience :: Developers
Classifier: Topic :: Software Development :: Libraries :: Python Modules
